nse_socket_client/__init__.py
nse_socket_client/nse_client.py
nse_socket_client-0.8.dist-info/LICENSE
nse_socket_client-0.8.dist-info/METADATA
nse_socket_client-0.8.dist-info/WHEEL
nse_socket_client-0.8.dist-info/top_level.txt
nse_socket_client-0.8.dist-info/RECORD
