Metadata-Version: 2.1
Name: nse-socket-client
Version: 0.8
Summary: UNKNOWN
Home-page: UNKNOWN
Author: siddid
License: UNKNOWN
Platform: UNKNOWN
Classifier: Development Status :: 5 - Production/Stable
Classifier: Intended Audience :: Developers
Classifier: Intended Audience :: Financial and Insurance Industry
Classifier: Topic :: Software Development :: Libraries :: Python Modules
Classifier: Topic :: Office/Business :: Financial :: Investment
Classifier: License :: OSI Approved :: MIT License
Classifier: Programming Language :: Python :: 3
Classifier: Programming Language :: Python :: 3.7
Classifier: Programming Language :: Python :: 3.8
Classifier: Programming Language :: Python :: 3.9
Classifier: Programming Language :: Python :: 3.10
Classifier: Programming Language :: Python :: 3.11
Classifier: Programming Language :: Python :: 3.12
Classifier: Operating System :: OS Independent
Requires-Python: >=3.7
License-File: LICENSE
Requires-Dist: requests (>=2.25.0)
Requires-Dist: websocket-client (>=1.0.0)
Provides-Extra: dev
Requires-Dist: black (>=21.0) ; extra == 'dev'
Requires-Dist: flake8 (>=3.8) ; extra == 'dev'
Requires-Dist: mypy (>=0.800) ; extra == 'dev'
Requires-Dist: pytest-cov (>=2.0) ; extra == 'dev'
Requires-Dist: pytest (>=6.0) ; extra == 'dev'
Provides-Extra: docs
Requires-Dist: sphinx-rtd-theme (>=1.0) ; extra == 'docs'
Requires-Dist: sphinx (>=4.0) ; extra == 'docs'
